metaprocessor/__init__.py
metaprocessor/cli.py
metaprocessor/commands/completion.py
metaprocessor/commands/config.py
metaprocessor/commands/metawear.py
metaprocessor/commands/object.py
metaprocessor/commands/run.py
metaprocessor/helpers/boto3.py
metaprocessor/helpers/completion.py
metaprocessor/helpers/config.py
metaprocessor/helpers/decorator.py
metaprocessor/helpers/metawear.py
metaprocessor/helpers/workflow.py
metaprocessor/libs/steps.py
metaprocessor/libs/uptime.py
metaprocessor-2023.1017.0.dist-info/METADATA
metaprocessor-2023.1017.0.dist-info/WHEEL
metaprocessor-2023.1017.0.dist-info/entry_points.txt
metaprocessor-2023.1017.0.dist-info/top_level.txt
metaprocessor-2023.1017.0.dist-info/RECORD
