Metadata-Version: 2.1
Name: metaprocessor
Version: 2023.1017.0
Summary: MetaProcessor, all-in-one data pipeline for MbientLab MetaWear series sensors!
Author-email: StepBroBD <Hi@StepBroBD.com>
License: MIT LICENCE
Project-URL: Documentation, https://metaprocessor.org
Project-URL: Repository, https://github.com/stepbrobd/metaprocessor
Project-URL: Issues, https://github.com/stepbrobd/metaprocessor/issues
Classifier: Environment :: Console
Classifier: Intended Audience :: Science/Research
Classifier: Programming Language :: Python
Classifier: Programming Language :: Python :: 3 :: Only
Requires-Python: >=3
Requires-Dist: boto3 >=1.26.79
Requires-Dist: click >=8.1.3
Requires-Dist: click-aliases >=1.0.1
Requires-Dist: click-option-group >=0.5.5
Requires-Dist: numpy >=1.24.2
Requires-Dist: pandas >=1.5.3
Requires-Dist: pyarrow >=12.0.0
Requires-Dist: rich >=13.3.5
Requires-Dist: scipy >=1.10.1
Requires-Dist: toml >=0.10.2
Requires-Dist: tqdm >=4.64.1
Requires-Dist: metawear >=1.0.8 ; platform_system == "Linux"
